asyncredis/__init__.py
asyncredis/connection.py
asyncredis/encoders.py
asyncredis/parser.py
asyncredis/redis.py
asyncredis-0.3.0.dist-info/METADATA
asyncredis-0.3.0.dist-info/WHEEL
asyncredis-0.3.0.dist-info/top_level.txt
asyncredis-0.3.0.dist-info/RECORD
