Metadata-Version: 2.1
Name: asyncredis
Version: 0.3.0
Summary: An asyncio compatible Redis driver. Just a pet-project.
Home-page: https://github.com/justanotherbyte/asyncredis
Author: justanotherbyte
License: MIT
Platform: UNKNOWN
Classifier: License :: OSI Approved :: MIT License
Classifier: Intended Audience :: Developers
Classifier: Natural Language :: English
Classifier: Operating System :: OS Independent
Classifier: Programming Language :: Python :: 3.8
Classifier: Programming Language :: Python :: 3.7
Classifier: Topic :: Internet
Classifier: Topic :: Software Development :: Libraries
Classifier: Topic :: Software Development :: Libraries :: Python Modules
Classifier: Topic :: Utilities
Requires-Python: >=3.7.0
Requires-Dist: hiredis (>=2.0.0)
